rsvidx/__init__.py
rsvidx/rsvidx.py
rsvidx/rsvidxlib.so
rsvidx-0.3.0.dist-info/LICENCE.md
rsvidx-0.3.0.dist-info/METADATA
rsvidx-0.3.0.dist-info/WHEEL
rsvidx-0.3.0.dist-info/top_level.txt
rsvidx-0.3.0.dist-info/RECORD
