Metadata-Version: 2.1
Name: rsvidx
Version: 0.3.0
Summary: Vector indexer
Home-page: https://github.com/RubenSystems/RSvIDX
Author: RubenSystems. Ruben Ticehurst-James.
Author-email: Ruben Ticehurst James <ruben@rubensystems.com>
Project-URL: Homepage, https://github.com/RubenSystems/RSvIDX
Keywords: ml,vector,semantic search,vector indexer,similarity search
License-File: LICENCE.md
